pim_loader/__init__.py
pim_loader/__main__.py
pim_loader/constants.py
pim_loader/pim_api.py
pim_loader-0.0.9.dist-info/METADATA
pim_loader-0.0.9.dist-info/WHEEL
pim_loader-0.0.9.dist-info/licenses/LICENSE
pim_loader-0.0.9.dist-info/RECORD
