Metadata-Version: 2.3
Name: pim_loader
Version: 0.0.9
Author-email: David Momeni <dav.momeni@gmail.com>
Classifier: License :: OSI Approved :: MIT License
Classifier: Operating System :: OS Independent
Classifier: Programming Language :: Python :: 3
Requires-Python: >=3.8
Requires-Dist: requests
Requires-Dist: rusta-tools
